contextender/__init__.py
contextender/config.py
contextender/contextend_by_mode.py
contextender/contextend_llm_request.py
contextender/py.typed
contextender/utils.py
contextender/list_item_chooser/__init__.py
contextender/list_item_chooser/item_chooser.py
contextender/list_item_chooser/prompts.py
contextender/summarizer/__init__.py
contextender/summarizer/prompts.py
contextender/summarizer/summarizer.py
contextender/text_item_chooser/__init__.py
contextender/text_item_chooser/item_chooser.py
contextender/text_item_chooser/prompts.py
contextender-0.1.1.dist-info/METADATA
contextender-0.1.1.dist-info/WHEEL
contextender-0.1.1.dist-info/licenses/LICENSE
contextender-0.1.1.dist-info/RECORD
