Metadata-Version: 2.4
Name: contextender
Version: 0.1.1
Summary: A framework for handling long LLM prompts possible exceeding the context length
Project-URL: Homepage, https://github.com/SL2000s/contextender
Project-URL: Issues, https://github.com/SL2000s/contextender/issues
Author: Simon Ljungbeck
License-Expression: MIT
License-File: LICENSE
Classifier: Operating System :: OS Independent
Classifier: Programming Language :: Python :: 3
Requires-Python: >=3.13
